osmpg/__init__.py
osmpg/__version__.py
osmpg-0.1.3.dist-info/METADATA
osmpg-0.1.3.dist-info/WHEEL
osmpg-0.1.3.dist-info/top_level.txt
osmpg-0.1.3.dist-info/RECORD
